{
  "unit": 1,
  "lesson_number": "1.7",
  "title": "Scientific Notation",
  "course": "MS Physics",
  "summary_sections": [
    {
      "title": "Lesson Overview",
      "content_html": "<h3>Overview</h3>\n<p>This lesson covers the fundamental measures of center used to analyze and summarize data sets. You'll learn how to calculate and apply the mean, median, and mode, and understand when each is most appropriate.</p>\n",
      "data_i18n": null
    },
    {
      "title": "Definitions and Concepts",
      "content_html": "<h3>Key Definitions</h3>\n<p><b>What is the purpose of scientific notation?</b></p>\n<p>Scientific notation is a way to write very large or very small numbers compactly using a coefficient multiplied by a power of 10. For example, 300,000,000 m/s becomes 3 × 10⁸ m/s, which is much easier to write and compare.</p>\n<p><b>What is 5,600,000 written in scientific notation?</b></p>\n<p>To convert 5,600,000 to scientific notation, move the decimal point 6 places to the left to get 5.6. Since you moved it 6 places, the exponent is 6. Therefore, 5,600,000 = 5.6 × 10⁶.</p>\n<p><b>What is 0.00032 written in scientific notation?</b></p>\n<p>To write 0.00032 in scientific notation, move the decimal point 4 places to the right to get 3.2. Since the original number is less than 1, the exponent is negative: 3.2 × 10⁻⁴.</p>\n<p><b>What is 7.3 × 10⁵ written in standard form?</b></p>\n<p>To convert 7.3 × 10⁵ to standard form, move the decimal point 5 places to the right. Starting with 7.3, this gives 730,000.</p>\n<p><b>What is 9.04 × 10⁻² written as a standard decimal?</b></p>\n<p>A negative exponent of −2 means the decimal moves 2 places to the left. Starting with 9.04, moving the decimal 2 places left gives 0.0904.</p>\n<p><b>What is a coefficient in scientific notation?</b></p>\n<p>The coefficient is the number between 1 and 10 that appears before the multiplication sign in scientific notation. For example, in 3.5 × 10⁸, the coefficient is 3.5.</p>\n<p><b>What is an exponent in scientific notation?</b></p>\n<p>The exponent in scientific notation is the power of 10 that indicates how many places the decimal point has been moved. A positive exponent means the decimal moved left (large number), and a negative exponent means it moved right (small number).</p>\n<p><b>What is standard form (standard notation)?</b></p>\n<p>Standard form (or standard notation) means writing a number in its regular decimal format with all digits shown. For example, 3.5 × 10⁴ in standard form is 35,000.</p>\n<p><b>What is a base in scientific notation?</b></p>\n<p>In scientific notation, the base is always 10. The notation takes the form coefficient × 10ⁿ, where 10 is the base and n is the exponent.</p>\n<p><b>What is a positive exponent in scientific notation?</b></p>\n<p>A positive exponent in scientific notation tells you the original number is 10 or greater. The decimal point moves to the right to produce a large number. For example, 6.2 × 10³ = 6,200.</p>\n<p><b>What is a negative exponent in scientific notation?</b></p>\n<p>A negative exponent indicates the original number is between 0 and 1. The decimal point shifts to the left to create a very small number. For example, 4.1 × 10⁻³ = 0.0041.</p>\n<p><b>A teacher asks students to arrange these distances from smallest to largest: 3.2 × 10⁻³ m, 1.5 × 10² m, 4.7 × 10⁻¹ m, 8.9 × 10⁰ m. What is the correct order?</b></p>\n<p>Converting each: 3.2 × 10⁻³ = 0.0032, 4.7 × 10⁻¹ = 0.47, 8.9 × 10⁰ = 8.9, 1.5 × 10² = 150. From smallest to largest: 0.0032, 0.47, 8.9, 150.</p>\n",
      "data_i18n": null
    }
  ]
}