{
  "unit": 4,
  "lesson_number": "4.1",
  "title": "Soil Formation and Composition",
  "course": "AP Environmental Science",
  "quiz_questions": [
    {
      "question_number": 1,
      "question_text": "Which of the following is the primary factor in the initial breakdown of rock into soil?",
      "attempted": 2,
      "data_i18n": null,
      "options": [
        {
          "text": "Evaporation",
          "is_correct": false,
          "data_i18n": null
        },
        {
          "text": "Weathering",
          "is_correct": true,
          "data_i18n": null
        },
        {
          "text": "Photosynthesis",
          "is_correct": false,
          "data_i18n": null
        },
        {
          "text": "Transpiration",
          "is_correct": false,
          "data_i18n": null
        }
      ],
      "explanation": "Weathering, both physical and chemical, is the primary process that breaks down parent rock (bedrock) into smaller particles that eventually form soil over time."
    },
    {
      "question_number": 2,
      "question_text": "What is the correct order of soil horizons from the surface downward?",
      "attempted": 2,
      "data_i18n": null,
      "options": [
        {
          "text": "A, O, C, B, R",
          "is_correct": false,
          "data_i18n": null
        },
        {
          "text": "R, C, B, A, O",
          "is_correct": false,
          "data_i18n": null
        },
        {
          "text": "O, A, B, C, R",
          "is_correct": true,
          "data_i18n": null
        },
        {
          "text": "C, B, A, R, O",
          "is_correct": false,
          "data_i18n": null
        }
      ],
      "explanation": "Soil horizons are arranged from the surface down as O (organic), A (topsoil), B (subsoil), C (weathered parent material), and R (bedrock), each with distinct compositions and characteristics."
    },
    {
      "question_number": 3,
      "question_text": "Which soil component is most important for providing nutrients to plants?",
      "attempted": 2,
      "data_i18n": null,
      "options": [
        {
          "text": "Bedrock fragments",
          "is_correct": false,
          "data_i18n": null
        },
        {
          "text": "Humus",
          "is_correct": true,
          "data_i18n": null
        },
        {
          "text": "Gravel",
          "is_correct": false,
          "data_i18n": null
        },
        {
          "text": "Sand particles",
          "is_correct": false,
          "data_i18n": null
        }
      ],
      "explanation": "Humus is decomposed organic matter that is rich in nutrients and has a high cation exchange capacity, making it the most important soil component for supplying plants with essential nutrients."
    },
    {
      "question_number": 4,
      "question_text": "Which soil particle size has the largest individual grains?",
      "attempted": 2,
      "data_i18n": null,
      "options": [
        {
          "text": "Clay",
          "is_correct": false,
          "data_i18n": null
        },
        {
          "text": "Sand",
          "is_correct": true,
          "data_i18n": null
        },
        {
          "text": "Humus",
          "is_correct": false,
          "data_i18n": null
        },
        {
          "text": "Silt",
          "is_correct": false,
          "data_i18n": null
        }
      ],
      "explanation": "Sand particles are the largest of the three mineral soil particle types, ranging from 0.05 to 2 mm in diameter, while silt particles are medium-sized and clay particles are the smallest."
    },
    {
      "question_number": 5,
      "question_text": "What type of organism is most responsible for mixing and aerating soil?",
      "attempted": 2,
      "data_i18n": null,
      "options": [
        {
          "text": "Earthworms",
          "is_correct": true,
          "data_i18n": null
        },
        {
          "text": "Algae",
          "is_correct": false,
          "data_i18n": null
        },
        {
          "text": "Birds",
          "is_correct": false,
          "data_i18n": null
        },
        {
          "text": "Fish",
          "is_correct": false,
          "data_i18n": null
        }
      ],
      "explanation": "Earthworms are often called ecosystem engineers because they burrow through soil, mixing organic and mineral layers, improving aeration, and enhancing water infiltration and drainage."
    },
    {
      "question_number": 6,
      "question_text": "Which of the five soil-forming factors refers to the type of bedrock from which soil develops?",
      "attempted": 2,
      "data_i18n": null,
      "options": [
        {
          "text": "Parent material",
          "is_correct": true,
          "data_i18n": null
        },
        {
          "text": "Topography",
          "is_correct": false,
          "data_i18n": null
        },
        {
          "text": "Time",
          "is_correct": false,
          "data_i18n": null
        },
        {
          "text": "Climate",
          "is_correct": false,
          "data_i18n": null
        }
      ],
      "explanation": "Parent material is the geological material (bedrock or deposited sediment) from which soil forms, and it strongly influences the mineral content, texture, and chemistry of the resulting soil."
    },
    {
      "question_number": 7,
      "question_text": "What percentage of soil volume in a typical healthy soil is composed of mineral particles?",
      "attempted": 2,
      "data_i18n": null,
      "options": [
        {
          "text": "About 45%",
          "is_correct": true,
          "data_i18n": null
        },
        {
          "text": "About 90%",
          "is_correct": false,
          "data_i18n": null
        },
        {
          "text": "About 25%",
          "is_correct": false,
          "data_i18n": null
        },
        {
          "text": "About 5%",
          "is_correct": false,
          "data_i18n": null
        }
      ],
      "explanation": "A typical healthy soil is approximately 45% mineral particles, 25% water, 25% air, and 5% organic matter by volume, though these proportions vary depending on soil type and conditions."
    },
    {
      "question_number": 8,
      "question_text": "Which horizon is commonly referred to as topsoil?",
      "attempted": 2,
      "data_i18n": null,
      "options": [
        {
          "text": "O horizon",
          "is_correct": false,
          "data_i18n": null
        },
        {
          "text": "B horizon",
          "is_correct": false,
          "data_i18n": null
        },
        {
          "text": "A horizon",
          "is_correct": true,
          "data_i18n": null
        },
        {
          "text": "C horizon",
          "is_correct": false,
          "data_i18n": null
        }
      ],
      "explanation": "The A horizon is commonly called topsoil and is characterized by a mixture of mineral particles and organic matter, making it the most fertile layer and the zone where most plant roots grow."
    },
    {
      "question_number": 9,
      "question_text": "How does climate primarily influence soil formation?",
      "attempted": 2,
      "data_i18n": null,
      "options": [
        {
          "text": "By changing the slope of the land",
          "is_correct": false,
          "data_i18n": null
        },
        {
          "text": "By determining the type of bedrock present",
          "is_correct": false,
          "data_i18n": null
        },
        {
          "text": "By controlling temperature and precipitation, which affect weathering rates",
          "is_correct": true,
          "data_i18n": null
        },
        {
          "text": "By directly adding minerals to the soil",
          "is_correct": false,
          "data_i18n": null
        }
      ],
      "explanation": "Climate influences soil formation primarily through temperature and precipitation, which control the rate of chemical weathering, biological activity, and the movement of water and dissolved substances through the soil profile."
    },
    {
      "question_number": 10,
      "question_text": "Which type of soil has the smallest particle size and holds the most water?",
      "attempted": 2,
      "data_i18n": null,
      "options": [
        {
          "text": "Clay soil",
          "is_correct": true,
          "data_i18n": null
        },
        {
          "text": "Sandy soil",
          "is_correct": false,
          "data_i18n": null
        },
        {
          "text": "Gravelly soil",
          "is_correct": false,
          "data_i18n": null
        },
        {
          "text": "Silty soil",
          "is_correct": false,
          "data_i18n": null
        }
      ],
      "explanation": "Clay particles are the smallest soil particles (less than 0.002 mm) and have a very high surface area, which allows clay soils to hold the most water and nutrients, though this also makes them poorly drained."
    },
    {
      "question_number": 11,
      "question_text": "What is the O horizon in a soil profile?",
      "attempted": 2,
      "data_i18n": null,
      "options": [
        {
          "text": "The zone of mineral accumulation below the topsoil",
          "is_correct": false,
          "data_i18n": null
        },
        {
          "text": "The layer of unweathered bedrock at the bottom of the soil profile",
          "is_correct": false,
          "data_i18n": null
        },
        {
          "text": "The layer of weathered parent material just above bedrock",
          "is_correct": false,
          "data_i18n": null
        },
        {
          "text": "The surface layer composed primarily of organic material such as leaf litter and decomposing matter",
          "is_correct": true,
          "data_i18n": null
        }
      ],
      "explanation": "The O horizon is the uppermost layer of soil, consisting primarily of organic matter in various stages of decomposition, including leaf litter, twigs, and humus."
    },
    {
      "question_number": 12,
      "question_text": "What does the term 'soil texture' refer to?",
      "attempted": 2,
      "data_i18n": null,
      "options": [
        {
          "text": "The relative proportions of sand, silt, and clay in the soil",
          "is_correct": true,
          "data_i18n": null
        },
        {
          "text": "The depth of the soil profile",
          "is_correct": false,
          "data_i18n": null
        },
        {
          "text": "The color of the soil",
          "is_correct": false,
          "data_i18n": null
        },
        {
          "text": "The amount of water the soil can hold",
          "is_correct": false,
          "data_i18n": null
        }
      ],
      "explanation": "Soil texture refers to the relative proportions of sand, silt, and clay particles in a soil sample, which determines many of the soil's physical properties including drainage, aeration, and water-holding capacity."
    },
    {
      "question_number": 13,
      "question_text": "What is 'loam' in the context of soil science?",
      "attempted": 2,
      "data_i18n": null,
      "options": [
        {
          "text": "A type of soil composed entirely of organic matter",
          "is_correct": false,
          "data_i18n": null
        },
        {
          "text": "A soil horizon found only in tropical regions",
          "is_correct": false,
          "data_i18n": null
        },
        {
          "text": "A type of rock that cannot form soil",
          "is_correct": false,
          "data_i18n": null
        },
        {
          "text": "A soil texture with a balanced mixture of sand, silt, and clay",
          "is_correct": true,
          "data_i18n": null
        }
      ],
      "explanation": "Loam is a soil texture classification that contains a relatively balanced mixture of sand, silt, and clay, typically considered ideal for agriculture because it retains moisture and nutrients while allowing adequate drainage and aeration."
    },
    {
      "question_number": 14,
      "question_text": "What does 'soil permeability' mean?",
      "attempted": 2,
      "data_i18n": null,
      "options": [
        {
          "text": "The ability of soil to resist erosion",
          "is_correct": false,
          "data_i18n": null
        },
        {
          "text": "The depth of the soil profile",
          "is_correct": false,
          "data_i18n": null
        },
        {
          "text": "The total amount of organic matter in soil",
          "is_correct": false,
          "data_i18n": null
        },
        {
          "text": "The rate at which water can pass through soil",
          "is_correct": true,
          "data_i18n": null
        }
      ],
      "explanation": "Soil permeability refers to how easily water moves through the soil, which is determined by pore size and connectivity; sandy soils have high permeability while clay soils have low permeability."
    },
    {
      "question_number": 15,
      "question_text": "What is meant by 'leaching' in soil science?",
      "attempted": 2,
      "data_i18n": null,
      "options": [
        {
          "text": "The process of soil compaction by heavy machinery",
          "is_correct": false,
          "data_i18n": null
        },
        {
          "text": "The growth of plant roots through soil layers",
          "is_correct": false,
          "data_i18n": null
        },
        {
          "text": "The downward movement of dissolved nutrients and minerals through soil by water",
          "is_correct": true,
          "data_i18n": null
        },
        {
          "text": "The addition of fertilizer to improve soil fertility",
          "is_correct": false,
          "data_i18n": null
        }
      ],
      "explanation": "Leaching is the process by which water percolating through the soil dissolves and carries away soluble minerals, nutrients, and organic compounds from upper soil layers to lower layers or into groundwater."
    },
    {
      "question_number": 16,
      "question_text": "What does 'pedogenesis' refer to?",
      "attempted": 2,
      "data_i18n": null,
      "options": [
        {
          "text": "The process of soil formation and development",
          "is_correct": true,
          "data_i18n": null
        },
        {
          "text": "The study of foot diseases",
          "is_correct": false,
          "data_i18n": null
        },
        {
          "text": "The erosion of soil by wind",
          "is_correct": false,
          "data_i18n": null
        },
        {
          "text": "The classification of rock types",
          "is_correct": false,
          "data_i18n": null
        }
      ],
      "explanation": "Pedogenesis is the scientific term for the natural process of soil formation, which involves the transformation of parent material through the combined effects of climate, organisms, topography, and time."
    },
    {
      "question_number": 17,
      "question_text": "What is the meaning of 'cation exchange capacity' (CEC) in soil?",
      "attempted": 2,
      "data_i18n": null,
      "options": [
        {
          "text": "The number of different organisms living in the soil",
          "is_correct": false,
          "data_i18n": null
        },
        {
          "text": "The total volume of air spaces in the soil",
          "is_correct": false,
          "data_i18n": null
        },
        {
          "text": "The speed at which water moves through the soil",
          "is_correct": false,
          "data_i18n": null
        },
        {
          "text": "The soil's ability to hold and exchange positively charged nutrient ions",
          "is_correct": true,
          "data_i18n": null
        }
      ],
      "explanation": "Cation exchange capacity is a measure of the soil's ability to hold and release positively charged ions (cations) such as calcium, magnesium, and potassium, which are essential plant nutrients; soils with high CEC are generally more fertile."
    },
    {
      "question_number": 18,
      "question_text": "What is 'soil porosity'?",
      "attempted": 2,
      "data_i18n": null,
      "options": [
        {
          "text": "The mineral content of the soil",
          "is_correct": false,
          "data_i18n": null
        },
        {
          "text": "The color variation between soil horizons",
          "is_correct": false,
          "data_i18n": null
        },
        {
          "text": "The resistance of soil to chemical weathering",
          "is_correct": false,
          "data_i18n": null
        },
        {
          "text": "The percentage of soil volume occupied by pore spaces",
          "is_correct": true,
          "data_i18n": null
        }
      ],
      "explanation": "Soil porosity is the proportion of total soil volume that consists of pore spaces (voids between soil particles), which are filled with air and water; porosity affects drainage, water storage, and root growth."
    },
    {
      "question_number": 19,
      "question_text": "What does 'soil horizon' mean?",
      "attempted": 2,
      "data_i18n": null,
      "options": [
        {
          "text": "A distinct horizontal layer in the soil profile with characteristic properties",
          "is_correct": true,
          "data_i18n": null
        },
        {
          "text": "The boundary between two different ecosystems",
          "is_correct": false,
          "data_i18n": null
        },
        {
          "text": "The visible surface of the ground",
          "is_correct": false,
          "data_i18n": null
        },
        {
          "text": "The maximum depth to which plant roots can grow",
          "is_correct": false,
          "data_i18n": null
        }
      ],
      "explanation": "A soil horizon is a distinct layer of soil that is roughly parallel to the surface and differs from adjacent layers in properties such as color, texture, structure, and chemical composition due to soil-forming processes."
    },
    {
      "question_number": 20,
      "question_text": "What does 'eluviation' mean in soil science?",
      "attempted": 2,
      "data_i18n": null,
      "options": [
        {
          "text": "The formation of bedrock into parent material",
          "is_correct": false,
          "data_i18n": null
        },
        {
          "text": "The decomposition of leaf litter on the soil surface",
          "is_correct": false,
          "data_i18n": null
        },
        {
          "text": "The accumulation of minerals in the B horizon",
          "is_correct": false,
          "data_i18n": null
        },
        {
          "text": "The washing out of fine particles, organic matter, and dissolved substances from the A horizon",
          "is_correct": true,
          "data_i18n": null
        }
      ],
      "explanation": "Eluviation is the process by which water moving downward through soil removes (washes out) fine clay particles, organic matter, and dissolved minerals from the A horizon, which is sometimes called the zone of eluviation."
    },
    {
      "question_number": 21,
      "question_text": "A farmer in the Midwest notices that one field produces significantly higher crop yields than an adjacent field despite receiving the same rainfall and fertilizer. Soil testing reveals that the productive field has loamy soil while the other has heavy clay soil. What is the most likely reason for the yield difference?",
      "attempted": 2,
      "data_i18n": null,
      "options": [
        {
          "text": "Loamy soil has no minerals and relies entirely on fertilizer",
          "is_correct": false,
          "data_i18n": null
        },
        {
          "text": "Loamy soil provides better drainage, aeration, and root penetration than clay soil",
          "is_correct": true,
          "data_i18n": null
        },
        {
          "text": "Clay soil has too many nutrients for crops to absorb",
          "is_correct": false,
          "data_i18n": null
        },
        {
          "text": "Clay soil contains no organic matter whatsoever",
          "is_correct": false,
          "data_i18n": null
        }
      ],
      "explanation": "Loamy soil has a balanced mix of sand, silt, and clay that provides excellent drainage and aeration while still retaining moisture and nutrients, allowing plant roots to grow easily and access water and nutrients more efficiently than in heavy clay soil."
    },
    {
      "question_number": 22,
      "question_text": "A geologist examines a road cut and observes that the soil is very thin, with only a faint A horizon directly overlying bedrock. The area is on a steep mountainside in a cold climate. Which soil-forming factor best explains why this soil is so poorly developed?",
      "attempted": 2,
      "data_i18n": null,
      "options": [
        {
          "text": "The soil has had too much time to develop",
          "is_correct": false,
          "data_i18n": null
        },
        {
          "text": "There are too many organisms in the area",
          "is_correct": false,
          "data_i18n": null
        },
        {
          "text": "The steep topography causes rapid erosion, preventing deep soil development",
          "is_correct": true,
          "data_i18n": null
        },
        {
          "text": "The parent material is too rich in nutrients",
          "is_correct": false,
          "data_i18n": null
        }
      ],
      "explanation": "Steep topography promotes rapid erosion and runoff, removing soil material faster than weathering and biological processes can build it up; combined with the cold climate slowing weathering rates, this results in thin, poorly developed soils."
    },
    {
      "question_number": 23,
      "question_text": "A homeowner plants a garden in soil that was recently filled in with material from a construction site. The plants grow poorly despite adequate watering and sunlight. Testing shows the soil is almost entirely sand. What soil property is most likely limiting plant growth?",
      "attempted": 2,
      "data_i18n": null,
      "options": [
        {
          "text": "Sandy soil blocks all sunlight from reaching the roots",
          "is_correct": false,
          "data_i18n": null
        },
        {
          "text": "The sandy soil has low water-holding capacity and low cation exchange capacity",
          "is_correct": true,
          "data_i18n": null
        },
        {
          "text": "Sandy soil prevents root growth entirely",
          "is_correct": false,
          "data_i18n": null
        },
        {
          "text": "The soil has too much water retention",
          "is_correct": false,
          "data_i18n": null
        }
      ],
      "explanation": "Sandy soil has large pore spaces that allow water to drain quickly, resulting in low water-holding capacity, and its low surface area gives it very low cation exchange capacity, meaning it cannot retain nutrients that plants need for growth."
    },
    {
      "question_number": 24,
      "question_text": "Scientists studying soils in a tropical rainforest find that despite lush vegetation, the soil's A and B horizons contain very few available nutrients. Most nutrients are stored in the living biomass. What process explains why the soil has such low nutrient levels?",
      "attempted": 2,
      "data_i18n": null,
      "options": [
        {
          "text": "Cold temperatures slow decomposition and lock nutrients in frozen soil",
          "is_correct": false,
          "data_i18n": null
        },
        {
          "text": "Volcanic activity continually destroys soil nutrients",
          "is_correct": false,
          "data_i18n": null
        },
        {
          "text": "Heavy rainfall causes intense leaching that washes nutrients from the soil",
          "is_correct": true,
          "data_i18n": null
        },
        {
          "text": "Tropical soils are too young to have accumulated nutrients",
          "is_correct": false,
          "data_i18n": null
        }
      ],
      "explanation": "In tropical rainforests, the combination of high temperatures accelerating decomposition and heavy rainfall causing intense leaching rapidly washes soluble nutrients out of the soil profile; the rapid nutrient cycling between decomposing organic matter and living plants keeps most nutrients in the biomass rather than the soil."
    },
    {
      "question_number": 25,
      "question_text": "A land developer clears a forested area and removes the top 30 cm of soil for a construction project. After construction, the developer tries to grow grass on the exposed subsoil but it fails to establish. Which explanation best accounts for this failure?",
      "attempted": 2,
      "data_i18n": null,
      "options": [
        {
          "text": "The B horizon has ideal conditions for grass establishment",
          "is_correct": false,
          "data_i18n": null
        },
        {
          "text": "Grass cannot grow in any area where trees previously grew",
          "is_correct": false,
          "data_i18n": null
        },
        {
          "text": "Subsoil contains too much organic matter for grass to grow",
          "is_correct": false,
          "data_i18n": null
        },
        {
          "text": "Removing the O and A horizons eliminated the organic matter and microbial communities essential for plant growth",
          "is_correct": true,
          "data_i18n": null
        }
      ],
      "explanation": "The O and A horizons contain the highest concentrations of organic matter, nutrients, and beneficial soil microorganisms that plants depend on; the B horizon (subsoil) is typically denser, less fertile, and lacks the microbial communities needed to support plant establishment."
    },
    {
      "question_number": 26,
      "question_text": "A soil scientist compares two soil samples from the same region: one from a flat prairie and one from a nearby hillside. The prairie soil has thick, dark A and B horizons, while the hillside soil is thin with poorly defined horizons. What best explains this difference?",
      "attempted": 2,
      "data_i18n": null,
      "options": [
        {
          "text": "The hillside has different parent material",
          "is_correct": false,
          "data_i18n": null
        },
        {
          "text": "The hillside receives more rainfall than the prairie",
          "is_correct": false,
          "data_i18n": null
        },
        {
          "text": "The flat terrain of the prairie allows soil accumulation, while slope erosion limits soil development on the hillside",
          "is_correct": true,
          "data_i18n": null
        },
        {
          "text": "The prairie soil is younger than the hillside soil",
          "is_correct": false,
          "data_i18n": null
        }
      ],
      "explanation": "Topography significantly affects soil development; flat areas like prairies accumulate sediment and organic matter, allowing deep soil profiles to form, while sloped areas experience erosion that removes soil material and prevents thick horizon development."
    },
    {
      "question_number": 27,
      "question_text": "An environmental consultant is hired to assess soil at a former industrial site for a planned community garden. Soil tests reveal high levels of lead and cadmium in the A horizon. What is the most appropriate recommendation?",
      "attempted": 2,
      "data_i18n": null,
      "options": [
        {
          "text": "Plant crops immediately since metals improve soil fertility",
          "is_correct": false,
          "data_i18n": null
        },
        {
          "text": "Ignore the metals because they will leach away within a few weeks",
          "is_correct": false,
          "data_i18n": null
        },
        {
          "text": "Remove or remediate the contaminated topsoil before planting food crops",
          "is_correct": true,
          "data_i18n": null
        },
        {
          "text": "Add more sand to dilute the metal concentrations",
          "is_correct": false,
          "data_i18n": null
        }
      ],
      "explanation": "Heavy metals like lead and cadmium persist in soil for very long periods and can be taken up by food crops, posing serious health risks to humans; contaminated soil must be removed, treated, or capped before growing edible plants."
    },
    {
      "question_number": 28,
      "question_text": "A volcanic island that emerged from the ocean 200 years ago has thin, rocky soil with only a few pioneer plant species growing in crevices. A nearby older island has deep, fertile soil supporting dense forests. What soil-forming factor primarily explains the difference in soil development between the two islands?",
      "attempted": 2,
      "data_i18n": null,
      "options": [
        {
          "text": "Human agricultural practices on the older island",
          "is_correct": false,
          "data_i18n": null
        },
        {
          "text": "Time, because soil formation is a very slow process",
          "is_correct": true,
          "data_i18n": null
        },
        {
          "text": "Climate differences between the islands",
          "is_correct": false,
          "data_i18n": null
        },
        {
          "text": "Different parent material on each island",
          "is_correct": false,
          "data_i18n": null
        }
      ],
      "explanation": "Time is a critical soil-forming factor; soil development from bare rock to a mature profile with distinct horizons can take hundreds to thousands of years, explaining why the young volcanic island has minimal soil compared to the older established island."
    },
    {
      "question_number": 29,
      "question_text": "A watershed manager discovers that after heavy rains, a local stream becomes extremely turbid (muddy). Investigation reveals that nearby farmland has exposed clay-rich soil with no vegetation cover. Which soil property is most directly responsible for the turbidity problem?",
      "attempted": 2,
      "data_i18n": null,
      "options": [
        {
          "text": "Fine clay particles are easily transported by runoff into the stream",
          "is_correct": true,
          "data_i18n": null
        },
        {
          "text": "High soil porosity allowing water to infiltrate too quickly",
          "is_correct": false,
          "data_i18n": null
        },
        {
          "text": "Large sand particles roll downhill into the stream",
          "is_correct": false,
          "data_i18n": null
        },
        {
          "text": "The soil's high organic matter content dissolves in water",
          "is_correct": false,
          "data_i18n": null
        }
      ],
      "explanation": "Clay particles are extremely fine and light, making them easily suspended in water and transported by surface runoff; without vegetation to hold the soil in place, rain washes these particles into streams, causing high turbidity."
    },
    {
      "question_number": 30,
      "question_text": "An agricultural extension agent advises a farmer to add lime (calcium carbonate) to acidic soil before planting crops. The farmer asks why this is necessary. What is the best explanation the agent could provide?",
      "attempted": 2,
      "data_i18n": null,
      "options": [
        {
          "text": "Lime replaces the need for all other fertilizers",
          "is_correct": false,
          "data_i18n": null
        },
        {
          "text": "Lime raises soil pH, making nutrients more available and reducing toxic aluminum levels",
          "is_correct": true,
          "data_i18n": null
        },
        {
          "text": "Lime physically breaks up clay particles to improve drainage",
          "is_correct": false,
          "data_i18n": null
        },
        {
          "text": "Lime increases soil acidity to help crops grow faster",
          "is_correct": false,
          "data_i18n": null
        }
      ],
      "explanation": "Adding lime to acidic soil raises the pH toward neutral, which increases the availability of essential nutrients like nitrogen, phosphorus, and potassium, and reduces the solubility of toxic aluminum that can damage plant roots in acidic conditions."
    }
  ]
}