{
  "unit": 5,
  "lesson_number": "5.2",
  "title": "Exponential Decay",
  "course": "Algebra 1",
  "quiz_questions": [
    {
      "question_number": 1,
      "question_text": "Exponential decay requires the base b to satisfy:",
      "attempted": 2,
      "data_i18n": null,
      "options": [
        { "text": "b > 1", "is_correct": false, "data_i18n": null },
        { "text": "0 < b < 1", "is_correct": true, "data_i18n": null },
        { "text": "b = 1", "is_correct": false, "data_i18n": null },
        { "text": "b < 0", "is_correct": false, "data_i18n": null }
      ],
      "explanation": "For exponential decay, the base must be between 0 and 1 (exclusive). This ensures the output decreases as x increases, since multiplying by a fraction less than 1 produces a smaller result."
    },
    {
      "question_number": 2,
      "question_text": "If a car loses 15% of its value each year, the decay factor is:",
      "attempted": 2,
      "data_i18n": null,
      "options": [
        { "text": "0.15", "is_correct": false, "data_i18n": null },
        { "text": "1.15", "is_correct": false, "data_i18n": null },
        { "text": "0.85", "is_correct": true, "data_i18n": null },
        { "text": "0.50", "is_correct": false, "data_i18n": null }
      ],
      "explanation": "The decay factor b = 1 − r = 1 − 0.15 = 0.85. Losing 15% each year means retaining 85% of the previous value, so the multiplier is 0.85."
    },
    {
      "question_number": 3,
      "question_text": "In y = 1000(0.9)ˣ, the initial value is:",
      "attempted": 2,
      "data_i18n": null,
      "options": [
        { "text": "0.9", "is_correct": false, "data_i18n": null },
        { "text": "1000", "is_correct": true, "data_i18n": null },
        { "text": "900", "is_correct": false, "data_i18n": null },
        { "text": "100", "is_correct": false, "data_i18n": null }
      ],
      "explanation": "When x = 0, y = 1000(0.9)⁰ = 1000 · 1 = 1000. The coefficient 'a' in an exponential function is the initial value, representing the output when x = 0."
    },
    {
      "question_number": 4,
      "question_text": "What is 500(0.8)³?",
      "attempted": 2,
      "data_i18n": null,
      "options": [
        { "text": "256", "is_correct": true, "data_i18n": null },
        { "text": "320", "is_correct": false, "data_i18n": null },
        { "text": "400", "is_correct": false, "data_i18n": null },
        { "text": "200", "is_correct": false, "data_i18n": null }
      ],
      "explanation": "500(0.8)³ = 500 × 0.512 = 256. Calculate 0.8³ = 0.8 × 0.8 × 0.8 = 0.512, then multiply by 500."
    },
    {
      "question_number": 5,
      "question_text": "A decay factor of 0.7 means what percent is lost each period?",
      "attempted": 2,
      "data_i18n": null,
      "options": [
        { "text": "70%", "is_correct": false, "data_i18n": null },
        { "text": "7%", "is_correct": false, "data_i18n": null },
        { "text": "30%", "is_correct": true, "data_i18n": null },
        { "text": "3%", "is_correct": false, "data_i18n": null }
      ],
      "explanation": "The decay rate r = 1 − b = 1 − 0.7 = 0.3 = 30%. A decay factor of 0.7 means 70% is retained and 30% is lost each period."
    },
    {
      "question_number": 6,
      "question_text": "The horizontal asymptote of y = 200(0.5)ˣ is:",
      "attempted": 2,
      "data_i18n": null,
      "options": [
        { "text": "y = 200", "is_correct": false, "data_i18n": null },
        { "text": "y = 0", "is_correct": true, "data_i18n": null },
        { "text": "y = 0.5", "is_correct": false, "data_i18n": null },
        { "text": "y = 100", "is_correct": false, "data_i18n": null }
      ],
      "explanation": "For any basic exponential function y = a · bˣ with no vertical shift, the horizontal asymptote is y = 0. The function decreases toward zero but never actually reaches it."
    },
    {
      "question_number": 7,
      "question_text": "Which equation models exponential decay?",
      "attempted": 2,
      "data_i18n": null,
      "options": [
        { "text": "y = 100(1.05)ˣ", "is_correct": false, "data_i18n": null },
        { "text": "y = 100(0.95)ˣ", "is_correct": true, "data_i18n": null },
        { "text": "y = 100x − 5", "is_correct": false, "data_i18n": null },
        { "text": "y = 100 · 5ˣ", "is_correct": false, "data_i18n": null }
      ],
      "explanation": "Exponential decay has the form y = a · bˣ where 0 < b < 1. The base 0.95 is between 0 and 1, so y = 100(0.95)ˣ models decay. The other exponential options have bases greater than 1."
    },
    {
      "question_number": 8,
      "question_text": "In y = 800(0.75)ˣ, after 2 periods the value is:",
      "attempted": 2,
      "data_i18n": null,
      "options": [
        { "text": "600", "is_correct": false, "data_i18n": null },
        { "text": "450", "is_correct": true, "data_i18n": null },
        { "text": "400", "is_correct": false, "data_i18n": null },
        { "text": "337.50", "is_correct": false, "data_i18n": null }
      ],
      "explanation": "y = 800(0.75)² = 800 × 0.5625 = 450. After the first period the value is 600, and after the second period it is 600 × 0.75 = 450."
    },
    {
      "question_number": 9,
      "question_text": "A substance has a half-life of 1 hour. The decay factor per hour is:",
      "attempted": 2,
      "data_i18n": null,
      "options": [
        { "text": "2", "is_correct": false, "data_i18n": null },
        { "text": "0.5", "is_correct": true, "data_i18n": null },
        { "text": "0.25", "is_correct": false, "data_i18n": null },
        { "text": "1.5", "is_correct": false, "data_i18n": null }
      ],
      "explanation": "A half-life means half the substance remains after each period, so the decay factor is 0.5. Multiplying by 0.5 each hour cuts the amount in half."
    },
    {
      "question_number": 10,
      "question_text": "As x increases in an exponential decay function, the y-values:",
      "attempted": 2,
      "data_i18n": null,
      "options": [
        { "text": "Increase without bound", "is_correct": false, "data_i18n": null },
        { "text": "Decrease toward zero", "is_correct": true, "data_i18n": null },
        { "text": "Stay constant", "is_correct": false, "data_i18n": null },
        { "text": "Become negative", "is_correct": false, "data_i18n": null }
      ],
      "explanation": "In exponential decay (0 < b < 1), each multiplication by b produces a smaller positive value. The outputs approach zero but remain positive, never reaching zero or becoming negative."
    },
    {
      "question_number": 11,
      "question_text": "What is exponential decay?",
      "attempted": 2,
      "data_i18n": null,
      "options": [
        { "text": "A decrease by a constant amount each period", "is_correct": false, "data_i18n": null },
        { "text": "A decrease by a constant percentage or factor each period, modeled by y = a · bˣ where 0 < b < 1", "is_correct": true, "data_i18n": null },
        { "text": "Any function that has a negative slope", "is_correct": false, "data_i18n": null },
        { "text": "A function that equals zero at some point", "is_correct": false, "data_i18n": null }
      ],
      "explanation": "Exponential decay is a pattern where a quantity decreases by the same percentage or factor each time period. It is modeled by y = a · bˣ with 0 < b < 1, producing a curve that drops rapidly at first and then levels off toward zero."
    },
    {
      "question_number": 12,
      "question_text": "What is a decay factor?",
      "attempted": 2,
      "data_i18n": null,
      "options": [
        { "text": "The amount subtracted each period", "is_correct": false, "data_i18n": null },
        { "text": "The base b (where 0 < b < 1) by which the output is multiplied each period", "is_correct": true, "data_i18n": null },
        { "text": "The rate at which a function increases", "is_correct": false, "data_i18n": null },
        { "text": "The y-intercept of the decay function", "is_correct": false, "data_i18n": null }
      ],
      "explanation": "The decay factor is the base b in the exponential decay function y = a · bˣ, where 0 < b < 1. It represents the fraction of the quantity that remains after each time period."
    },
    {
      "question_number": 13,
      "question_text": "What is a decay rate?",
      "attempted": 2,
      "data_i18n": null,
      "options": [
        { "text": "The same as the decay factor", "is_correct": false, "data_i18n": null },
        { "text": "The percentage lost each period, calculated as r = 1 − b", "is_correct": true, "data_i18n": null },
        { "text": "The total amount lost over all time", "is_correct": false, "data_i18n": null },
        { "text": "The initial value of the function", "is_correct": false, "data_i18n": null }
      ],
      "explanation": "The decay rate r is the fraction or percentage of the quantity that is lost each period. It is found by r = 1 − b, where b is the decay factor. For example, b = 0.85 gives a decay rate of 15%."
    },
    {
      "question_number": 14,
      "question_text": "What is a half-life?",
      "attempted": 2,
      "data_i18n": null,
      "options": [
        { "text": "The time it takes for a quantity to double", "is_correct": false, "data_i18n": null },
        { "text": "The time it takes for a quantity to decrease to half its current amount", "is_correct": true, "data_i18n": null },
        { "text": "Half of the initial value", "is_correct": false, "data_i18n": null },
        { "text": "The point where the graph crosses the x-axis", "is_correct": false, "data_i18n": null }
      ],
      "explanation": "A half-life is the time required for a quantity undergoing exponential decay to decrease to exactly half of its current value. It is commonly used in radioactive decay and pharmacology."
    },
    {
      "question_number": 15,
      "question_text": "What does depreciation mean?",
      "attempted": 2,
      "data_i18n": null,
      "options": [
        { "text": "An increase in the value of an asset over time", "is_correct": false, "data_i18n": null },
        { "text": "A decrease in the value of an asset over time", "is_correct": true, "data_i18n": null },
        { "text": "The original purchase price of an asset", "is_correct": false, "data_i18n": null },
        { "text": "The interest earned on an investment", "is_correct": false, "data_i18n": null }
      ],
      "explanation": "Depreciation is the loss of value of an asset (such as a car or piece of equipment) over time. It is often modeled using exponential decay, where the value decreases by a fixed percentage each year."
    },
    {
      "question_number": 16,
      "question_text": "What is the horizontal asymptote of a basic exponential decay function?",
      "attempted": 2,
      "data_i18n": null,
      "options": [
        { "text": "The line y = a (the initial value)", "is_correct": false, "data_i18n": null },
        { "text": "The line y = 0 (the x-axis)", "is_correct": true, "data_i18n": null },
        { "text": "The line x = 0 (the y-axis)", "is_correct": false, "data_i18n": null },
        { "text": "There is no horizontal asymptote", "is_correct": false, "data_i18n": null }
      ],
      "explanation": "For a basic exponential decay function y = a · bˣ with no vertical shift, the horizontal asymptote is y = 0. The function values get closer and closer to zero but never actually equal zero."
    },
    {
      "question_number": 17,
      "question_text": "What does 'end behavior' describe for an exponential decay function as x approaches infinity?",
      "attempted": 2,
      "data_i18n": null,
      "options": [
        { "text": "The function approaches infinity", "is_correct": false, "data_i18n": null },
        { "text": "The function approaches zero from above", "is_correct": true, "data_i18n": null },
        { "text": "The function approaches the initial value", "is_correct": false, "data_i18n": null },
        { "text": "The function becomes negative", "is_correct": false, "data_i18n": null }
      ],
      "explanation": "End behavior describes what happens to the function values as x gets very large. For exponential decay, as x approaches infinity, the output y approaches 0 from above, meaning it gets smaller and smaller but stays positive."
    },
    {
      "question_number": 18,
      "question_text": "What is the range of y = a · bˣ when a > 0 and 0 < b < 1?",
      "attempted": 2,
      "data_i18n": null,
      "options": [
        { "text": "All real numbers", "is_correct": false, "data_i18n": null },
        { "text": "y ≤ a", "is_correct": false, "data_i18n": null },
        { "text": "y > 0", "is_correct": true, "data_i18n": null },
        { "text": "0 ≤ y ≤ a", "is_correct": false, "data_i18n": null }
      ],
      "explanation": "When a > 0 and 0 < b < 1, the function always produces positive outputs. As x increases, y approaches but never reaches 0, and as x decreases, y grows without bound. So the range is y > 0."
    },
    {
      "question_number": 19,
      "question_text": "What does 'retained value' mean in a depreciation context?",
      "attempted": 2,
      "data_i18n": null,
      "options": [
        { "text": "The original purchase price", "is_correct": false, "data_i18n": null },
        { "text": "The amount of value an asset keeps after depreciation, equal to the original value times the decay factor", "is_correct": true, "data_i18n": null },
        { "text": "The total depreciation over all years", "is_correct": false, "data_i18n": null },
        { "text": "The interest earned on the asset", "is_correct": false, "data_i18n": null }
      ],
      "explanation": "Retained value is the portion of an asset's worth that remains after depreciation. If an asset depreciates by 20% per year (decay factor 0.80), then 80% of the value is retained each year."
    },
    {
      "question_number": 20,
      "question_text": "What is the difference between exponential decay and linear decrease?",
      "attempted": 2,
      "data_i18n": null,
      "options": [
        { "text": "They are the same thing", "is_correct": false, "data_i18n": null },
        { "text": "Linear decrease subtracts a constant amount while exponential decay multiplies by a constant factor less than 1", "is_correct": true, "data_i18n": null },
        { "text": "Exponential decay subtracts a constant amount while linear decrease multiplies", "is_correct": false, "data_i18n": null },
        { "text": "Exponential decay always decreases faster than linear", "is_correct": false, "data_i18n": null }
      ],
      "explanation": "Linear decrease subtracts the same fixed amount each period (constant rate of change), while exponential decay multiplies by the same fraction each period (constant multiplicative change). Exponential decay decreases quickly at first, then slows down."
    },
    {
      "question_number": 21,
      "question_text": "A new car is purchased for $30,000 and depreciates at 12% per year. What is the car's value after 3 years?",
      "attempted": 2,
      "data_i18n": null,
      "options": [
        { "text": "$19,200.00", "is_correct": false, "data_i18n": null },
        { "text": "Approximately $20,440.32", "is_correct": true, "data_i18n": null },
        { "text": "$22,500.00", "is_correct": false, "data_i18n": null },
        { "text": "Approximately $23,232.00", "is_correct": false, "data_i18n": null }
      ],
      "explanation": "V = 30000(0.88)³ = 30000 × 0.681472 ≈ $20,440.32. The decay factor is 1 − 0.12 = 0.88, and after 3 years the car retains about 68.1% of its original value."
    },
    {
      "question_number": 22,
      "question_text": "A patient takes 400 mg of medicine. The body eliminates 25% of the remaining medicine each hour. How much remains after 2 hours?",
      "attempted": 2,
      "data_i18n": null,
      "options": [
        { "text": "200 mg", "is_correct": false, "data_i18n": null },
        { "text": "225 mg", "is_correct": true, "data_i18n": null },
        { "text": "250 mg", "is_correct": false, "data_i18n": null },
        { "text": "300 mg", "is_correct": false, "data_i18n": null }
      ],
      "explanation": "M = 400(0.75)² = 400 × 0.5625 = 225 mg. Losing 25% each hour means retaining 75%, so the decay factor is 0.75. After 2 hours, 56.25% of the original dose remains."
    },
    {
      "question_number": 23,
      "question_text": "A radioactive isotope has a half-life of 3 years. If a sample starts with 160 grams, how much remains after 9 years?",
      "attempted": 2,
      "data_i18n": null,
      "options": [
        { "text": "40 grams", "is_correct": false, "data_i18n": null },
        { "text": "20 grams", "is_correct": true, "data_i18n": null },
        { "text": "10 grams", "is_correct": false, "data_i18n": null },
        { "text": "80 grams", "is_correct": false, "data_i18n": null }
      ],
      "explanation": "In 9 years, there are 9 / 3 = 3 half-lives. After each half-life the amount is halved: 160 → 80 → 40 → 20 grams. Using the formula: 160(0.5)³ = 160 × 0.125 = 20 grams."
    },
    {
      "question_number": 24,
      "question_text": "A laptop purchased for $1,200 depreciates at 20% per year. What is its value after 4 years?",
      "attempted": 2,
      "data_i18n": null,
      "options": [
        { "text": "$491.52", "is_correct": true, "data_i18n": null },
        { "text": "$480.00", "is_correct": false, "data_i18n": null },
        { "text": "$614.40", "is_correct": false, "data_i18n": null },
        { "text": "$240.00", "is_correct": false, "data_i18n": null }
      ],
      "explanation": "V = 1200(0.80)⁴ = 1200 × 0.4096 = $491.52. The decay factor is 1 − 0.20 = 0.80, and after 4 years the laptop has retained about 41% of its original value."
    },
    {
      "question_number": 25,
      "question_text": "A bouncing ball is dropped from 10 meters. Each bounce reaches 60% of the previous height. What height does it reach after the 3rd bounce?",
      "attempted": 2,
      "data_i18n": null,
      "options": [
        { "text": "3.6 meters", "is_correct": false, "data_i18n": null },
        { "text": "2.16 meters", "is_correct": true, "data_i18n": null },
        { "text": "1.80 meters", "is_correct": false, "data_i18n": null },
        { "text": "4.00 meters", "is_correct": false, "data_i18n": null }
      ],
      "explanation": "Height after 3 bounces = 10(0.60)³ = 10 × 0.216 = 2.16 meters. Each bounce reaches 60% of the previous height, so the decay factor is 0.60."
    },
    {
      "question_number": 26,
      "question_text": "A town's lake had 500 fish. Due to pollution, the fish population decreases by 10% per month. Approximately how many fish remain after 6 months?",
      "attempted": 2,
      "data_i18n": null,
      "options": [
        { "text": "Approximately 266", "is_correct": true, "data_i18n": null },
        { "text": "200", "is_correct": false, "data_i18n": null },
        { "text": "300", "is_correct": false, "data_i18n": null },
        { "text": "Approximately 354", "is_correct": false, "data_i18n": null }
      ],
      "explanation": "F = 500(0.90)⁶ = 500 × 0.531441 ≈ 266 fish. The decay factor is 0.90 (retaining 90% each month), and after 6 months about 53.1% of the original population remains."
    },
    {
      "question_number": 27,
      "question_text": "A cup of hot coffee at 180°F cools such that the temperature above room temperature (70°F) decreases by 15% each minute. What is the coffee's temperature after 2 minutes?",
      "attempted": 2,
      "data_i18n": null,
      "options": [
        { "text": "Approximately 150°F", "is_correct": false, "data_i18n": null },
        { "text": "Approximately 149.5°F", "is_correct": true, "data_i18n": null },
        { "text": "Approximately 130°F", "is_correct": false, "data_i18n": null },
        { "text": "Approximately 160°F", "is_correct": false, "data_i18n": null }
      ],
      "explanation": "The excess temperature is 180 − 70 = 110°F. After 2 minutes: excess = 110(0.85)² = 110 × 0.7225 = 79.475°F. Total temperature = 70 + 79.475 ≈ 149.5°F."
    },
    {
      "question_number": 28,
      "question_text": "A company's old inventory of 2,000 units sells off at a rate where 30% is sold each week. Approximately how many units remain unsold after 3 weeks?",
      "attempted": 2,
      "data_i18n": null,
      "options": [
        { "text": "686", "is_correct": true, "data_i18n": null },
        { "text": "800", "is_correct": false, "data_i18n": null },
        { "text": "200", "is_correct": false, "data_i18n": null },
        { "text": "980", "is_correct": false, "data_i18n": null }
      ],
      "explanation": "U = 2000(0.70)³ = 2000 × 0.343 = 686 units. Selling 30% per week means 70% remains each week, giving a decay factor of 0.70."
    },
    {
      "question_number": 29,
      "question_text": "A researcher measures 800 grams of a substance that decays by 40% per day. After how many full days will there be less than 200 grams?",
      "attempted": 2,
      "data_i18n": null,
      "options": [
        { "text": "2 days", "is_correct": false, "data_i18n": null },
        { "text": "3 days", "is_correct": true, "data_i18n": null },
        { "text": "4 days", "is_correct": false, "data_i18n": null },
        { "text": "5 days", "is_correct": false, "data_i18n": null }
      ],
      "explanation": "Using y = 800(0.60)ᵗ: after 2 days y = 800(0.36) = 288 (still above 200), after 3 days y = 800(0.216) = 172.8 (below 200). So after 3 full days there will be less than 200 grams."
    },
    {
      "question_number": 30,
      "question_text": "A smartphone's resale value was $900 new. Two years later it is worth $576. Assuming exponential decay, what is the annual decay factor?",
      "attempted": 2,
      "data_i18n": null,
      "options": [
        { "text": "0.64", "is_correct": false, "data_i18n": null },
        { "text": "0.75", "is_correct": false, "data_i18n": null },
        { "text": "0.80", "is_correct": true, "data_i18n": null },
        { "text": "0.85", "is_correct": false, "data_i18n": null }
      ],
      "explanation": "576 = 900 · b², so b² = 576/900 = 0.64, and b = √0.64 = 0.80. The phone retains 80% of its value each year, meaning a 20% annual depreciation rate."
    }
  ]
}
